xcmp/__init__.py
xcmp/commands/__init__.py
xcmp/commands/file.py
xcmp/utils/__init__.py
xcmp-0.1a1.dist-info/LICENSE
xcmp-0.1a1.dist-info/METADATA
xcmp-0.1a1.dist-info/WHEEL
xcmp-0.1a1.dist-info/entry_points.txt
xcmp-0.1a1.dist-info/top_level.txt
xcmp-0.1a1.dist-info/zip-safe
xcmp-0.1a1.dist-info/RECORD
