Metadata-Version: 2.1
Name: xcmp
Version: 0.1a1
Summary: Compare any objects.
Home-page: https://github.com/bondbox/xcmp
Author: Mingzhe Zou
Author-email: zoumingzhe@outlook.com
License: MIT
Project-URL: Source Code, https://github.com/bondbox/xcmp
Project-URL: Bug Tracker, https://github.com/bondbox/xcmp/issues
Project-URL: Documentation, https://github.com/bondbox/xcmp
Keywords: compare
Platform: any
Classifier: Programming Language :: Python
Classifier: Programming Language :: Python :: 3
Requires-Python: >=3.8
Requires-Dist: humanize
Requires-Dist: xarg-python (>=0.10)
